LICENSE
README.md
setup.cfg
setup.py
src/pytest_inmanta_yang/__init__.py
src/pytest_inmanta_yang/const.py
src/pytest_inmanta_yang/fixtures.py
src/pytest_inmanta_yang/netconf_device_helper.py
src/pytest_inmanta_yang/object_element.py
src/pytest_inmanta_yang/parser.py
src/pytest_inmanta_yang/py.typed
src/pytest_inmanta_yang/yang_test.py
src/pytest_inmanta_yang.egg-info/PKG-INFO
src/pytest_inmanta_yang.egg-info/SOURCES.txt
src/pytest_inmanta_yang.egg-info/dependency_links.txt
src/pytest_inmanta_yang.egg-info/entry_points.txt
src/pytest_inmanta_yang.egg-info/requires.txt
src/pytest_inmanta_yang.egg-info/top_level.txt
src/pytest_inmanta_yang/clab/__init__.py
src/pytest_inmanta_yang/clab/config.py
src/pytest_inmanta_yang/clab/host.py
tests/test_clab_setup.py
tests/test_object_element.py
tests/test_tests_parameters.py