Metadata-Version: 2.1
Name: pytest-inmanta-yang
Version: 1.4.0
Summary: Common fixtures used in inmanta yang related modules
Author: Inmanta NV
Author-email: code@inmanta.com
License: Apache License, Version 2.0
Classifier: Development Status :: 4 - Beta
Classifier: Framework :: Pytest
Classifier: Intended Audience :: Developers
Classifier: Topic :: Software Development :: Testing
Classifier: Programming Language :: Python
Classifier: Programming Language :: Python :: 2
Classifier: Programming Language :: Python :: 2.7
Classifier: Programming Language :: Python :: 3
Classifier: Programming Language :: Python :: 3.4
Classifier: Programming Language :: Python :: 3.5
Classifier: Programming Language :: Python :: 3.6
Classifier: Programming Language :: Python :: 3.9
Classifier: Programming Language :: Python :: Implementation :: CPython
Classifier: Programming Language :: Python :: Implementation :: PyPy
Classifier: Operating System :: OS Independent
Classifier: License :: OSI Approved :: Apache Software License
Requires-Python: >=2.7, !=3.0.*, !=3.1.*, !=3.2.*, !=3.3.*
License-File: LICENSE
Requires-Dist: lxml
Requires-Dist: ncclient
Requires-Dist: pyang==2.5.3
Requires-Dist: pytest
Requires-Dist: requests
Requires-Dist: scrapli
Requires-Dist: paramiko
Requires-Dist: inmanta-core
Requires-Dist: pytest-inmanta
